LICENSE.txt
README.md
setup.py
economic/__init__.py
economic/account_entries.py
economic/accounting_years.py
economic/auth.py
economic/customer_groups.py
economic/customers.py
economic/departmental_distributions.py
economic/employees.py
economic/invoices.py
economic/products.py
economic/query.py
economic/serializer.py
economic/utils.py
python_economic_rest.egg-info/PKG-INFO
python_economic_rest.egg-info/SOURCES.txt
python_economic_rest.egg-info/dependency_links.txt
python_economic_rest.egg-info/not-zip-safe
python_economic_rest.egg-info/top_level.txt